nstaff/Notes.md
nstaff/README.md
nstaff/__init__.py
nstaff/conftest.py
nstaff/dir_structure.py
nstaff/installer.py
nstaff/requirements.txt
nstaff/speedboat.py
nstaff/assets/__init__.py
nstaff/assets/company-logo.png
nstaff/assets/favicon.ico
nstaff/assets/report_chart_javascript_snippet.js
nstaff/assets/report_chart_js_dataset_and_config_snippet.js
nstaff/assets/chartjs/3_2_1/package/LICENSE.md
nstaff/assets/chartjs/3_2_1/package/README.md
nstaff/assets/chartjs/3_2_1/package/package.json
nstaff/assets/chartjs/3_2_1/package/auto/auto.esm.d.ts
nstaff/assets/chartjs/3_2_1/package/auto/auto.esm.js
nstaff/assets/chartjs/3_2_1/package/auto/auto.js
nstaff/assets/chartjs/3_2_1/package/auto/package.json
nstaff/assets/chartjs/3_2_1/package/dist/chart.esm.js
nstaff/assets/chartjs/3_2_1/package/dist/chart.js
nstaff/assets/chartjs/3_2_1/package/dist/chart.min.js
nstaff/assets/chartjs/3_2_1/package/dist/helpers.esm.js
nstaff/assets/chartjs/3_2_1/package/dist/chunks/helpers.segment.js
nstaff/assets/chartjs/3_2_1/package/helpers/helpers.esm.d.ts
nstaff/assets/chartjs/3_2_1/package/helpers/helpers.esm.js
nstaff/assets/chartjs/3_2_1/package/helpers/helpers.js
nstaff/assets/chartjs/3_2_1/package/helpers/package.json
nstaff/assets/chartjs/3_2_1/package/types/adapters.d.ts
nstaff/assets/chartjs/3_2_1/package/types/animation.d.ts
nstaff/assets/chartjs/3_2_1/package/types/basic.d.ts
nstaff/assets/chartjs/3_2_1/package/types/color.d.ts
nstaff/assets/chartjs/3_2_1/package/types/element.d.ts
nstaff/assets/chartjs/3_2_1/package/types/geometric.d.ts
nstaff/assets/chartjs/3_2_1/package/types/index.esm.d.ts
nstaff/assets/chartjs/3_2_1/package/types/layout.d.ts
nstaff/assets/chartjs/3_2_1/package/types/utils.d.ts
nstaff/assets/chartjs/3_2_1/package/types/helpers/helpers.canvas.d.ts
nstaff/assets/chartjs/3_2_1/package/types/helpers/helpers.collection.d.ts
nstaff/assets/chartjs/3_2_1/package/types/helpers/helpers.color.d.ts
nstaff/assets/chartjs/3_2_1/package/types/helpers/helpers.core.d.ts
nstaff-0.1.2.dist-info/METADATA
nstaff-0.1.2.dist-info/WHEEL
nstaff-0.1.2.dist-info/RECORD
